{"stats":{"minecraft:picked_up":{"aindustries:ruby":7,"aindustries:raw_ruby":6,"minecraft:wheat_seeds":1},"minecraft:used":{"minecraft:stone_pickaxe":2,"aindustries:ruby_ore":5,"minecraft:iron_pickaxe":1,"minecraft:wooden_pickaxe":2,"minecraft:diamond_pickaxe":1,"aindustries:ruby_block":5},"minecraft:mined":{"minecraft:grass":4},"minecraft:custom":{"minecraft:jump":2,"minecraft:time_since_rest":6529,"minecraft:leave_game":1,"minecraft:sprint_one_cm":412,"minecraft:play_time":6529,"minecraft:time_since_death":6529,"minecraft:walk_one_cm":5004,"minecraft:total_world_time":6616,"minecraft:fly_one_cm":373}},"DataVersion":3578}